CHANGELOG
INSTALLATION
LICENSE
MANIFEST.in
README
TODO
setup.cfg
setup.py
bin/cachePilots.sh
bin/cacheSC.sh
bin/cacheSchedConfig.py
cacheschedconfig/CacheSchedConfig.py
cacheschedconfig/OraDBProxy2.py
cacheschedconfig/__init__.py
cron/cachepilot
cron/cacheschedconfig
etc/cachepilot-sysconfig
etc/cacheschedconfig-sysconfig
panda_cacheschedconfig.egg-info/PKG-INFO
panda_cacheschedconfig.egg-info/SOURCES.txt
panda_cacheschedconfig.egg-info/dependency_links.txt
panda_cacheschedconfig.egg-info/top_level.txt