Metadata-Version: 1.2
Name: panda-cacheschedconfig
Version: 1.3.8
Summary: panda-cacheschedconfig package
Home-page: https://twiki.cern.ch/twiki/bin/view/Atlas/PanDA
Author: Panda Team
Author-email: atlas-adc-panda-support@cern.ch
Maintainer: Panda Team
Maintainer-email: atlas-adc-panda-support@cern.ch
License: GPL
Platform: UNKNOWN
